stllrent_bootstrap/__init__.py
stllrent_bootstrap/exc.py
stllrent_bootstrap/celery/app.py
stllrent_bootstrap/celery/app_logger.py
stllrent_bootstrap/celery/base_task.py
stllrent_bootstrap/celery/bootsteps.py
stllrent_bootstrap/celery/config/settings.py
stllrent_bootstrap/celery/model/brokers.py
stllrent_bootstrap/celery/model/task_queues_factory.py
stllrent_bootstrap/celery/notification/email.py
stllrent_bootstrap/celery/notification/trigger.py
stllrent_bootstrap/database/discovery.py
stllrent_bootstrap/database/manager.py
stllrent_bootstrap/database/session.py
stllrent_bootstrap/database/model/core.py
stllrent_bootstrap/flask/app_factory.py
stllrent_bootstrap/flask/app_logger.py
stllrent_bootstrap/flask/app_settings.py
stllrent_bootstrap/workflow/api.py
stllrent_bootstrap/workflow/config/flow_config.py
stllrent_bootstrap/workflow/model/enums.py
stllrent_bootstrap/workflow/model/task.py
stllrent_bootstrap/workflow/model/workflow.py
stllrent_bootstrap/workflow/model/schema/task.py
stllrent_bootstrap/workflow/model/schema/workflow.py
stllrent_bootstrap-1.1.11.dist-info/METADATA
stllrent_bootstrap-1.1.11.dist-info/WHEEL
stllrent_bootstrap-1.1.11.dist-info/top_level.txt
stllrent_bootstrap-1.1.11.dist-info/RECORD
