Metadata-Version: 2.4
Name: stllrent-bootstrap
Version: 1.1.11
Summary: Comprehensive Python module designed to standardize and accelerate the development of responsive Flask APIs that leverage Celery for asynchronous workload processing
Author-email: Marcus Rodrigues Magalhães <marcusrodrigues.magalhaes@stellantis.com>
Classifier: Programming Language :: Python :: 3
Classifier: License :: OSI Approved :: MIT License
Classifier: Operating System :: OS Independent
Requires-Python: >=3.11
Requires-Dist: celery==5.5.*
Requires-Dist: pydantic-settings==2.9.*
Requires-Dist: sqlalchemy==2.0.*
Requires-Dist: psycopg2-binary==2.9.*
Requires-Dist: Flask==3.1.*
Requires-Dist: requests==2.31.*
Requires-Dist: pydantic==2.11.*
Requires-Dist: python-json-logger==3.3.*
Requires-Dist: Deprecated==1.2.18
Provides-Extra: dev
Requires-Dist: pytest==8.2.*; extra == "dev"
Requires-Dist: pytest-mock==3.12.*; extra == "dev"
Requires-Dist: PyQt5>=5.15.10; extra == "dev"
Requires-Dist: pytest-cov==4.1.0; extra == "dev"
Requires-Dist: pytest-xdist>=2.2.0; extra == "dev"
Requires-Dist: pytest-qt>=4.2.0; extra == "dev"
